manim_voiceover_plus/__init__.py
manim_voiceover_plus/defaults.py
manim_voiceover_plus/helper.py
manim_voiceover_plus/modify_audio.py
manim_voiceover_plus/services/__init__.py
manim_voiceover_plus/services/azure.py
manim_voiceover_plus/services/base.py
manim_voiceover_plus/services/coqui.py
manim_voiceover_plus/services/elevenlabs.py
manim_voiceover_plus/services/gtts.py
manim_voiceover_plus/services/openai.py
manim_voiceover_plus/services/pyttsx3.py
manim_voiceover_plus/services/recorder/__init__.py
manim_voiceover_plus/services/recorder/utility.py
manim_voiceover_plus/services/stitcher.py
manim_voiceover_plus/tracker.py
manim_voiceover_plus/translate/__init__.py
manim_voiceover_plus/translate/gettext_utils.py
manim_voiceover_plus/translate/render.py
manim_voiceover_plus/translate/translate.py
manim_voiceover_plus/voiceover_scene.py
manim_voiceover_plus-0.6.9.dist-info/LICENSE
manim_voiceover_plus-0.6.9.dist-info/METADATA
manim_voiceover_plus-0.6.9.dist-info/WHEEL
manim_voiceover_plus-0.6.9.dist-info/entry_points.txt
manim_voiceover_plus-0.6.9.dist-info/RECORD
